{"shipClasses":{"25":{"name":"Frigate","namePlural":"Frigates"},"26":{"name":"Cruiser","namePlural":"Cruisers"},"27":{"name":"Battleship","namePlural":"Battleships"},"28":{"name":"Industrial","namePlural":"Industrials"},"29":{"name":"Capsule","namePlural":"Capsules"},"30":{"name":"Titan","namePlural":"Titans"},"31":{"name":"Shuttle","namePlural":"Shuttles"},"237":{"name":"Rookie ship","namePlural":"Rookie ships"},"324":{"name":"Assault Frigate","namePlural":"Assault Frigates"},"358":{"name":"Heavy Assault Cruiser","namePlural":"Heavy Assault Cruisers"},"380":{"name":"Deep Space Transport","namePlural":"Deep Space Transports"},"381":{"name":"Elite Battleship","namePlural":"Elite Battleships"},"419":{"name":"Combat Battlecruiser","namePlural":"Combat Battlecruisers"},"420":{"name":"Destroyer","namePlural":"Destroyers"},"463":{"name":"Mining Barge","namePlural":"Mining Barges"},"485":{"name":"Dreadnought","namePlural":"Dreadnoughts"},"513":{"name":"Freighter","namePlural":"Freighters"},"540":{"name":"Command Ship","namePlural":"Command Ships"},"541":{"name":"Interdictor","namePlural":"Interdictors"},"543":{"name":"Exhumer","namePlural":"Exhumers"},"547":{"name":"Carrier","namePlural":"Carriers"},"659":{"name":"Supercarrier","namePlural":"Supercarriers"},"830":{"name":"Covert Ops","namePlural":"Covert Ops"},"831":{"name":"Interceptor","namePlural":"Interceptors"},"832":{"name":"Logistics","namePlural":"Logistics"},"833":{"name":"Force Recon Ship","namePlural":"Force Recon Ships"},"834":{"name":"Stealth Bomber","namePlural":"Stealth Bombers"},"883":{"name":"Capital Industrial Ship","namePlural":"Capital Industrial Ships"},"893":{"name":"Electronic Attack Ship","namePlural":"Electronic Attack Ships"},"894":{"name":"Heavy Interdiction Cruiser","namePlural":"Heavy Interdiction Cruisers"},"898":{"name":"Black Ops","namePlural":"Black Ops"},"900":{"name":"Marauder","namePlural":"Marauders"},"902":{"name":"Jump Freighter","namePlural":"Jump Freighters"},"906":{"name":"Combat Recon Ship","namePlural":"Combat Recon Ships"},"941":{"name":"Industrial Command Ship","namePlural":"Industrial Command Ships"},"963":{"name":"Strategic Cruiser","namePlural":"Strategic Cruisers"},"1022":{"name":"Prototype Exploration Ship","namePlural":"Prototype Exploration Ships"},"1201":{"name":"Attack Battlecruiser","namePlural":"Attack Battlecruisers"},"1202":{"name":"Blockade Runner","namePlural":"Blockade Runners"},"1283":{"name":"Expedition Frigate","namePlural":"Expedition Frigates"},"1305":{"name":"Tactical Destroyer","namePlural":"Tactical Destroyers"},"1527":{"name":"Logistics Frigate","namePlural":"Logistics Frigates"},"1534":{"name":"Command Destroyer","namePlural":"Command Destroyers"},"1538":{"name":"Force Auxiliary","namePlural":"Force Auxiliaries"}},"ships":{"582":{"name":"Bantam","class":25},"583":{"name":"Condor","class":25},"584":{"name":"Griffin","class":25},"585":{"name":"Slasher","class":25},"586":{"name":"Probe","class":25},"587":{"name":"Rifter","class":25},"588":{"name":"Reaper","class":237},"589":{"name":"Executioner","class":25},"590":{"name":"Inquisitor","class":25},"591":{"name":"Tormentor","class":25},"592":{"name":"Navitas","class":25},"593":{"name":"Tristan","class":25},"594":{"name":"Incursus","class":25},"595":{"name":"Gallente Police Ship","class":25},"596":{"name":"Impairor","class":237},"597":{"name":"Punisher","class":25},"598":{"name":"Breacher","class":25},"599":{"name":"Burst","class":25},"600":{"name":"Minmatar Peacekeeper Ship","class":25},"601":{"name":"Ibis","class":237},"602":{"name":"Kestrel","class":25},"603":{"name":"Merlin","class":25},"605":{"name":"Heron","class":25},"606":{"name":"Velator","class":237},"607":{"name":"Imicus","class":25},"608":{"name":"Atron","class":25},"609":{"name":"Maulus","class":25},"613":{"name":"Devourer","class":25},"614":{"name":"Fury","class":25},"615":{"name":"Immolator","class":237},"616":{"name":"Medusa","class":25},"617":{"name":"Echo","class":237},"618":{"name":"Lynx","class":25},"619":{"name":"Swordspine","class":25},"620":{"name":"Osprey","class":26},"621":{"name":"Caracal","class":26},"622":{"name":"Stabber","class":26},"623":{"name":"Moa","class":26},"624":{"name":"Maller","class":26},"625":{"name":"Augoror","class":26},"626":{"name":"Vexor","class":26},"627":{"name":"Thorax","class":26},"628":{"name":"Arbitrator","class":26},"629":{"name":"Rupture","class":26},"630":{"name":"Bellicose","class":26},"631":{"name":"Scythe","class":26},"632":{"name":"Blackbird","class":26},"633":{"name":"Celestis","class":26},"634":{"name":"Exequror","class":26},"635":{"name":"Opux Luxury Yacht","class":26},"638":{"name":"Raven","class":27},"639":{"name":"Tempest","class":27},"640":{"name":"Scorpion","class":27},"641":{"name":"Megathron","class":27},"642":{"name":"Apocalypse","class":27},"643":{"name":"Armageddon","class":27},"644":{"name":"Typhoon","class":27},"645":{"name":"Dominix","class":27},"648":{"name":"Badger","class":28},"649":{"name":"Tayra","class":28},"650":{"name":"Nereus","class":28},"651":{"name":"Hoarder","class":28},"652":{"name":"Mammoth","class":28},"653":{"name":"Wreathe","class":28},"654":{"name":"Kryos","class":28},"655":{"name":"Epithal","class":28},"656":{"name":"Miasmos","class":28},"657":{"name":"Iteron Mark V","class":28},"670":{"name":"Capsule","class":29},"671":{"name":"Erebus","class":30},"672":{"name":"Caldari Shuttle","class":31},"1233":{"name":"Polaris Enigma Frigate","class":237},"1896":{"name":"Concord Police Frigate","class":25},"1898":{"name":"Concord SWAT Frigate","class":25},"1900":{"name":"Concord Army Frigate","class":25},"1902":{"name":"Concord Special Ops Frigate","class":25},"1904":{"name":"Concord Police Cruiser","class":26},"1912":{"name":"Concord Police Battleship","class":27},"1914":{"name":"Concord Special Ops Battleship","class":27},"1916":{"name":"Concord SWAT Battleship","class":27},"1918":{"name":"Concord Army Battleship","class":27},"1944":{"name":"Bestower","class":28},"2006":{"name":"Omen","class":26},"2078":{"name":"Zephyr","class":1022},"2161":{"name":"Crucifier","class":25},"2834":{"name":"Utu","class":324},"2836":{"name":"Adrestia","class":358},"2863":{"name":"Primae","class":28},"2998":{"name":"Noctis","class":28},"3514":{"name":"Revenant","class":659},"3516":{"name":"Malice","class":324},"3518":{"name":"Vangel","class":358},"3532":{"name":"Echelon","class":25},"3628":{"name":"Nation","class":659},"3751":{"name":"SOCT 1","class":25},"3753":{"name":"SOCT 2","class":25},"3756":{"name":"Gnosis","class":419},"3764":{"name":"Leviathan","class":30},"3766":{"name":"Vigil","class":25},"3768":{"name":"Amarr Police Frigate","class":25},"4005":{"name":"Scorpion Ishukone Watch","class":27},"4302":{"name":"Oracle","class":1201},"4306":{"name":"Naga","class":1201},"4308":{"name":"Talos","class":1201},"4310":{"name":"Tornado","class":1201},"4363":{"name":"Miasmos Quafe Ultra Edition","class":28},"4388":{"name":"Miasmos Quafe Ultramarine Edition","class":28},"9854":{"name":"Polaris Inspector Frigate","class":237},"9858":{"name":"Polaris Centurion TEST","class":237},"9860":{"name":"Polaris Legatus Frigate","class":237},"9862":{"name":"Polaris Centurion Frigate","class":237},"11011":{"name":"Guardian-Vexor","class":26},"11019":{"name":"Cockroach","class":25},"11129":{"name":"Gallente Shuttle","class":31},"11132":{"name":"Minmatar Shuttle","class":31},"11134":{"name":"Amarr Shuttle","class":31},"11172":{"name":"Helios","class":830},"11174":{"name":"Keres","class":893},"11176":{"name":"Crow","class":831},"11178":{"name":"Raptor","class":831},"11182":{"name":"Cheetah","class":830},"11184":{"name":"Crusader","class":831},"11186":{"name":"Malediction","class":831},"11188":{"name":"Anathema","class":830},"11190":{"name":"Sentinel","class":893},"11192":{"name":"Buzzard","class":830},"11194":{"name":"Kitsune","class":893},"11196":{"name":"Claw","class":831},"11198":{"name":"Stiletto","class":831},"11200":{"name":"Taranis","class":831},"11202":{"name":"Ares","class":831},"11365":{"name":"Vengeance","class":324},"11371":{"name":"Wolf","class":324},"11373":{"name":"Blade","class":324},"11375":{"name":"Erinye","class":324},"11377":{"name":"Nemesis","class":834},"11379":{"name":"Hawk","class":324},"11381":{"name":"Harpy","class":324},"11383":{"name":"Gatherer","class":324},"11387":{"name":"Hyena","class":893},"11389":{"name":"Kishar","class":324},"11393":{"name":"Retribution","class":324},"11400":{"name":"Jaguar","class":324},"11567":{"name":"Avatar","class":30},"11936":{"name":"Apocalypse Imperial Issue","class":27},"11938":{"name":"Armageddon Imperial Issue","class":27},"11940":{"name":"Gold Magnate","class":25},"11942":{"name":"Silver Magnate","class":25},"11957":{"name":"Falcon","class":833},"11959":{"name":"Rook","class":906},"11961":{"name":"Huginn","class":906},"11963":{"name":"Rapier","class":833},"11965":{"name":"Pilgrim","class":833},"11969":{"name":"Arazu","class":833},"11971":{"name":"Lachesis","class":906},"11978":{"name":"Scimitar","class":832},"11985":{"name":"Basilisk","class":832},"11987":{"name":"Guardian","class":832},"11989":{"name":"Oneiros","class":832},"11993":{"name":"Cerberus","class":358},"11995":{"name":"Onyx","class":894},"11999":{"name":"Vagabond","class":358},"12003":{"name":"Zealot","class":358},"12005":{"name":"Ishtar","class":358},"12011":{"name":"Eagle","class":358},"12013":{"name":"Broadsword","class":894},"12015":{"name":"Muninn","class":358},"12017":{"name":"Devoter","class":894},"12019":{"name":"Sacrilege","class":358},"12021":{"name":"Phobos","class":894},"12023":{"name":"Deimos","class":358},"12032":{"name":"Manticore","class":834},"12034":{"name":"Hound","class":834},"12036":{"name":"Dagger","class":324},"12038":{"name":"Purifier","class":834},"12042":{"name":"Ishkur","class":324},"12044":{"name":"Enyo","class":324},"12729":{"name":"Crane","class":1202},"12731":{"name":"Bustard","class":380},"12733":{"name":"Prorator","class":1202},"12735":{"name":"Prowler","class":1202},"12743":{"name":"Viator","class":1202},"12745":{"name":"Occator","class":380},"12747":{"name":"Mastodon","class":380},"12753":{"name":"Impel","class":380},"13202":{"name":"Megathron Federate Issue","class":27},"16227":{"name":"Ferox","class":419},"16229":{"name":"Brutix","class":419},"16231":{"name":"Cyclone","class":419},"16233":{"name":"Prophecy","class":419},"16236":{"name":"Coercer","class":420},"16238":{"name":"Cormorant","class":420},"16240":{"name":"Catalyst","class":420},"16242":{"name":"Thrasher","class":420},"17360":{"name":"Immovable Enigma","class":25},"17476":{"name":"Covetor","class":463},"17478":{"name":"Retriever","class":463},"17480":{"name":"Procurer","class":463},"17619":{"name":"Caldari Navy Hookbill","class":25},"17634":{"name":"Caracal Navy Issue","class":26},"17636":{"name":"Raven Navy Issue","class":27},"17703":{"name":"Imperial Navy Slicer","class":25},"17705":{"name":"Khanid Navy Frigate","class":25},"17707":{"name":"Mordus Frigate","class":25},"17709":{"name":"Omen Navy Issue","class":26},"17713":{"name":"Stabber Fleet Issue","class":26},"17715":{"name":"Gila","class":26},"17718":{"name":"Phantasm","class":26},"17720":{"name":"Cynabal","class":26},"17722":{"name":"Vigilant","class":26},"17726":{"name":"Apocalypse Navy Issue","class":27},"17728":{"name":"Megathron Navy Issue","class":27},"17732":{"name":"Tempest Fleet Issue","class":27},"17736":{"name":"Nightmare","class":27},"17738":{"name":"Machariel","class":27},"17740":{"name":"Vindicator","class":27},"17812":{"name":"Republic Fleet Firetail","class":25},"17841":{"name":"Federation Navy Comet","class":25},"17843":{"name":"Vexor Navy Issue","class":26},"17918":{"name":"Rattlesnake","class":27},"17920":{"name":"Bhaalgorn","class":27},"17922":{"name":"Ashimmu","class":26},"17924":{"name":"Succubus","class":25},"17926":{"name":"Cruor","class":25},"17928":{"name":"Daredevil","class":25},"17930":{"name":"Worm","class":25},"17932":{"name":"Dramiel","class":25},"19720":{"name":"Revelation","class":485},"19722":{"name":"Naglfar","class":485},"19724":{"name":"Moros","class":485},"19726":{"name":"Phoenix","class":485},"19744":{"name":"Sigil","class":28},"20125":{"name":"Curse","class":906},"20183":{"name":"Providence","class":513},"20185":{"name":"Charon","class":513},"20187":{"name":"Obelisk","class":513},"20189":{"name":"Fenrir","class":513},"21097":{"name":"Goru's Shuttle","class":31},"21628":{"name":"Guristas Shuttle","class":31},"22428":{"name":"Redeemer","class":898},"22430":{"name":"Sin","class":898},"22436":{"name":"Widow","class":898},"22440":{"name":"Panther","class":898},"22442":{"name":"Eos","class":540},"22444":{"name":"Sleipnir","class":540},"22446":{"name":"Vulture","class":540},"22448":{"name":"Absolution","class":540},"22452":{"name":"Heretic","class":541},"22456":{"name":"Sabre","class":541},"22460":{"name":"Eris","class":541},"22464":{"name":"Flycatcher","class":541},"22466":{"name":"Astarte","class":540},"22468":{"name":"Claymore","class":540},"22470":{"name":"Nighthawk","class":540},"22474":{"name":"Damnation","class":540},"22544":{"name":"Hulk","class":543},"22546":{"name":"Skiff","class":543},"22548":{"name":"Mackinaw","class":543},"22852":{"name":"Hel","class":659},"23757":{"name":"Archon","class":547},"23773":{"name":"Ragnarok","class":30},"23911":{"name":"Thanatos","class":547},"23913":{"name":"Nyx","class":659},"23915":{"name":"Chimera","class":547},"23917":{"name":"Wyvern","class":659},"23919":{"name":"Aeon","class":659},"24483":{"name":"Nidhoggur","class":547},"24688":{"name":"Rokh","class":27},"24690":{"name":"Hyperion","class":27},"24692":{"name":"Abaddon","class":27},"24694":{"name":"Maelstrom","class":27},"24696":{"name":"Harbinger","class":419},"24698":{"name":"Drake","class":419},"24700":{"name":"Myrmidon","class":419},"24702":{"name":"Hurricane","class":419},"25560":{"name":"Opux Dragoon Yacht","class":26},"26840":{"name":"Raven State Issue","class":27},"26842":{"name":"Tempest Tribal Issue","class":27},"27299":{"name":"Civilian Amarr Shuttle","class":31},"27301":{"name":"Civilian Caldari Shuttle","class":31},"27303":{"name":"Civilian Gallente Shuttle","class":31},"27305":{"name":"Civilian Minmatar Shuttle","class":31},"28352":{"name":"Rorqual","class":883},"28606":{"name":"Orca","class":941},"28659":{"name":"Paladin","class":900},"28661":{"name":"Kronos","class":900},"28665":{"name":"Vargur","class":900},"28710":{"name":"Golem","class":900},"28844":{"name":"Rhea","class":902},"28846":{"name":"Nomad","class":902},"28848":{"name":"Anshar","class":902},"28850":{"name":"Ark","class":902},"29248":{"name":"Magnate","class":25},"29266":{"name":"Apotheosis","class":31},"29328":{"name":"Amarr Media Shuttle","class":31},"29330":{"name":"Caldari Media Shuttle","class":31},"29332":{"name":"Gallente Media Shuttle","class":31},"29334":{"name":"Minmatar Media Shuttle","class":31},"29336":{"name":"Scythe Fleet Issue","class":26},"29337":{"name":"Augoror Navy Issue","class":26},"29340":{"name":"Osprey Navy Issue","class":26},"29344":{"name":"Exequror Navy Issue","class":26},"29984":{"name":"Tengu","class":963},"29986":{"name":"Legion","class":963},"29988":{"name":"Proteus","class":963},"29990":{"name":"Loki","class":963},"30842":{"name":"InterBus Shuttle","class":31},"32207":{"name":"Freki","class":324},"32209":{"name":"Mimir","class":358},"32305":{"name":"Armageddon Navy Issue","class":27},"32307":{"name":"Dominix Navy Issue","class":27},"32309":{"name":"Scorpion Navy Issue","class":27},"32311":{"name":"Typhoon Fleet Issue","class":27},"32788":{"name":"Cambion","class":324},"32790":{"name":"Etana","class":832},"32811":{"name":"Miasmos Amastris Edition","class":28},"32840":{"name":"InterBus Catalyst","class":420},"32842":{"name":"Intaki Syndicate Catalyst","class":420},"32844":{"name":"Inner Zone Shipping Catalyst","class":420},"32846":{"name":"Quafe Catalyst","class":420},"32848":{"name":"Aliastra Catalyst","class":420},"32872":{"name":"Algos","class":420},"32874":{"name":"Dragoon","class":420},"32876":{"name":"Corax","class":420},"32878":{"name":"Talwar","class":420},"32880":{"name":"Venture","class":25},"32983":{"name":"Sukuuvestaa Heron","class":25},"32985":{"name":"Inner Zone Shipping Imicus","class":25},"32987":{"name":"Sarum Magnate","class":25},"32989":{"name":"Vherokior Probe","class":25},"33079":{"name":"Hematos","class":237},"33081":{"name":"Taipan","class":237},"33083":{"name":"Violator","class":237},"33099":{"name":"Nefantar Thrasher","class":420},"33151":{"name":"Brutix Navy Issue","class":419},"33153":{"name":"Drake Navy Issue","class":419},"33155":{"name":"Harbinger Navy Issue","class":419},"33157":{"name":"Hurricane Fleet Issue","class":419},"33190":{"name":"Tash-Murkon Magnate","class":25},"33328":{"name":"Capsule - Genolution 'Auroral' 197-variant","class":29},"33395":{"name":"Moracha","class":833},"33397":{"name":"Chremoas","class":830},"33468":{"name":"Astero","class":25},"33470":{"name":"Stratios","class":26},"33472":{"name":"Nestor","class":27},"33513":{"name":"Leopard","class":31},"33553":{"name":"Stratios Emergency Responder","class":26},"33623":{"name":"Abaddon Tash-Murkon Edition","class":27},"33625":{"name":"Abaddon Kador Edition","class":27},"33627":{"name":"Rokh Nugoeihuvi Edition","class":27},"33629":{"name":"Rokh Wiyrkomi Edition","class":27},"33631":{"name":"Maelstrom Nefantar Edition","class":27},"33633":{"name":"Maelstrom Krusual Edition","class":27},"33635":{"name":"Hyperion Aliastra Edition","class":27},"33637":{"name":"Hyperion Inner Zone Shipping Edition","class":27},"33639":{"name":"Omen Kador Edition","class":26},"33641":{"name":"Omen Tash-Murkon Edition","class":26},"33643":{"name":"Caracal Nugoeihuvi Edition","class":26},"33645":{"name":"Caracal Wiyrkomi Edition","class":26},"33647":{"name":"Stabber Nefantar Edition","class":26},"33649":{"name":"Stabber Krusual Edition","class":26},"33651":{"name":"Thorax Aliastra Edition","class":26},"33653":{"name":"Thorax Inner Zone Shipping Edition","class":26},"33655":{"name":"Punisher Kador Edition","class":25},"33657":{"name":"Punisher Tash-Murkon Edition","class":25},"33659":{"name":"Merlin Nugoeihuvi Edition","class":25},"33661":{"name":"Merlin Wiyrkomi Edition","class":25},"33663":{"name":"Rifter Nefantar Edition","class":25},"33665":{"name":"Rifter Krusual Edition","class":25},"33667":{"name":"Incursus Aliastra Edition","class":25},"33669":{"name":"Incursus Inner Zone Shipping Edition","class":25},"33673":{"name":"Whiptail","class":831},"33675":{"name":"Chameleon","class":833},"33677":{"name":"Police Pursuit Comet","class":25},"33683":{"name":"Mackinaw ORE Development Edition","class":543},"33685":{"name":"Orca ORE Development Edition","class":941},"33687":{"name":"Rorqual ORE Development Edition","class":883},"33689":{"name":"Iteron Inner Zone Shipping Edition","class":28},"33691":{"name":"Tayra Wiyrkomi Edition","class":28},"33693":{"name":"Mammoth Nefantar Edition","class":28},"33695":{"name":"Bestower Tash-Murkon Edition","class":28},"33697":{"name":"Prospect","class":1283},"33816":{"name":"Garmur","class":25},"33818":{"name":"Orthrus","class":26},"33820":{"name":"Barghest","class":27},"33869":{"name":"Brutix Serpentis Edition","class":419},"33871":{"name":"Cyclone Thukker Tribe Edition","class":419},"33873":{"name":"Ferox Guristas Edition","class":419},"33875":{"name":"Prophecy Blood Raiders Edition","class":419},"33877":{"name":"Catalyst Serpentis Edition","class":420},"33879":{"name":"Coercer Blood Raiders Edition","class":420},"33881":{"name":"Cormorant Guristas Edition","class":420},"33883":{"name":"Thrasher Thukker Tribe Edition","class":420},"34118":{"name":"Megathron Quafe Edition","class":27},"34151":{"name":"Rattlesnake Victory Edition","class":27},"34213":{"name":"Apocalypse Blood Raider Edition","class":27},"34215":{"name":"Apocalypse Kador Edition","class":27},"34217":{"name":"Apocalypse Tash-Murkon Edition","class":27},"34219":{"name":"Paladin Blood Raider Edition","class":900},"34221":{"name":"Paladin Kador Edition","class":900},"34223":{"name":"Paladin Tash-Murkon Edition","class":900},"34225":{"name":"Raven Guristas Edition","class":27},"34227":{"name":"Raven Kaalakiota Edition","class":27},"34229":{"name":"Raven Nugoeihuvi Edition","class":27},"34231":{"name":"Golem Guristas Edition","class":900},"34233":{"name":"Golem Kaalakiota Edition","class":900},"34235":{"name":"Golem Nugoeihuvi Edition","class":900},"34237":{"name":"Megathron Police Edition","class":27},"34239":{"name":"Megathron Inner Zone Shipping Edition","class":27},"34241":{"name":"Kronos Police Edition","class":900},"34243":{"name":"Kronos Quafe Edition","class":900},"34245":{"name":"Kronos Inner Zone Shipping Edition","class":900},"34247":{"name":"Tempest Justice Edition","class":27},"34249":{"name":"Tempest Krusual Edition","class":27},"34251":{"name":"Tempest Nefantar Edition","class":27},"34253":{"name":"Vargur Justice Edition","class":900},"34255":{"name":"Vargur Krusual Edition","class":900},"34257":{"name":"Vargur Nefantar Edition","class":900},"34317":{"name":"Confessor","class":1305},"34328":{"name":"Bowhead","class":513},"34339":{"name":"Moros Interbus Edition","class":485},"34341":{"name":"Naglfar Justice Edition","class":485},"34343":{"name":"Phoenix Wiyrkomi Edition","class":485},"34345":{"name":"Revelation Sarum Edition","class":485},"34441":{"name":"Dominix Quafe Edition","class":27},"34443":{"name":"Tristan Quafe Edition","class":25},"34445":{"name":"Vexor Quafe Edition","class":26},"34457":{"name":"\u672b\u65e5\u6c99\u573a\u7ea7YC117\u5e74\u7279\u522b\u7248","class":27},"34459":{"name":"\u5730\u72f1\u5929\u4f7f\u7ea7YC117\u5e74\u7279\u522b\u7248","class":27},"34461":{"name":"\u9a6c\u514b\u745e\u7ea7YC117\u5e74\u7279\u522b\u7248","class":27},"34463":{"name":"\u54cd\u5c3e\u86c7\u7ea7YC117\u5e74\u7279\u522b\u7248","class":27},"34465":{"name":"\u591a\u7c73\u5c3c\u514b\u65af\u7ea7YC117\u5e74\u7279\u522b\u7248","class":27},"34467":{"name":"\u4e07\u738b\u5b9d\u5ea7\u7ea7YC117\u5e74\u7279\u522b\u7248","class":27},"34469":{"name":"\u4e4c\u9e26\u7ea7YC117\u5e74\u7279\u522b\u7248","class":27},"34471":{"name":"\u707e\u96be\u7ea7YC117\u5e74\u7279\u522b\u7248","class":27},"34473":{"name":"\u5e7c\u9f99\u7ea7YC117\u5e74\u7279\u522b\u7248","class":419},"34475":{"name":"\u6bd2\u8725\u7ea7YC117\u5e74\u7279\u522b\u7248","class":26},"34477":{"name":"\u94f6\u9e70\u7ea7YC117\u5e74\u7279\u522b\u7248","class":358},"34479":{"name":"\u4f0a\u4ec0\u5854\u7ea7YC117\u5e74\u7279\u522b\u7248","class":358},"34496":{"name":"Council Diplomatic Shuttle","class":31},"34562":{"name":"Svipul","class":1305},"34590":{"name":"Victorieux Luxury Yacht","class":26},"34828":{"name":"Jackdaw","class":1305},"35683":{"name":"Hecate","class":1305},"35779":{"name":"Imp","class":831},"35781":{"name":"Fiend","class":894},"37135":{"name":"Endurance","class":1283},"37453":{"name":"Crucifier Navy Issue","class":25},"37454":{"name":"Vigil Fleet Issue","class":25},"37455":{"name":"Griffin Navy Issue","class":25},"37456":{"name":"Maulus Navy Issue","class":25},"37457":{"name":"Deacon","class":1527},"37458":{"name":"Kirin","class":1527},"37459":{"name":"Thalia","class":1527},"37460":{"name":"Scalpel","class":1527},"37480":{"name":"Bifrost","class":1534},"37481":{"name":"Pontifex","class":1534},"37482":{"name":"Stork","class":1534},"37483":{"name":"Magus","class":1534},"37604":{"name":"Apostle","class":1538},"37605":{"name":"Minokawa","class":1538},"37606":{"name":"Lif","class":1538},"37607":{"name":"Ninazu","class":1538}}}